{
  "indexes": [
    {
      "collectionGroup": "crates",
      "queryScope": "COLLECTION_GROUP",
      "fields": [
        {
          "fieldPath": "ownerId",
          "order": "ASCENDING"
        },
        {
          "fieldPath": "createdAt",
          "order": "DESCENDING"
        },
        {
          "fieldPath": "__name__",
          "order": "DESCENDING"
        }
      ]
    },
    {
      "collectionGroup": "crates",
      "queryScope": "COLLECTION_GROUP",
      "fields": [
        {
          "fieldPath": "ownerId",
          "order": "ASCENDING"
        },
        {
          "fieldPath": "searchField",
          "order": "ASCENDING"
        },
        {
          "fieldPath": "__name__",
          "order": "ASCENDING"
        }
      ]
    },
    {
      "collectionGroup": "crates",
      "queryScope": "COLLECTION_GROUP",
      "fields": [
        {
          "fieldPath": "tags",
          "arrayConfig": "CONTAINS"
        },
        {
          "fieldPath": "ownerId",
          "order": "ASCENDING"
        },
        {
          "fieldPath": "searchField",
          "order": "ASCENDING"
        },
        {
          "fieldPath": "__name__",
          "order": "ASCENDING"
        }
      ]
    },
    {
      "collectionGroup": "feedbackTemplates",
      "queryScope": "COLLECTION_GROUP",
      "fields": [
        {
          "fieldPath": "ownerId",
          "order": "ASCENDING"
        },
        {
          "fieldPath": "createdAt",
          "order": "DESCENDING"
        },
        {
          "fieldPath": "__name__",
          "order": "DESCENDING"
        }
      ]
    },
    {
      "collectionGroup": "feedbackTemplates",
      "queryScope": "COLLECTION_GROUP",
      "fields": [
        {
          "fieldPath": "isPublic",
          "order": "ASCENDING"
        },
        {
          "fieldPath": "createdAt",
          "order": "DESCENDING"
        },
        {
          "fieldPath": "__name__",
          "order": "DESCENDING"
        }
      ]
    },
    {
      "collectionGroup": "feedbackResponses",
      "queryScope": "COLLECTION_GROUP",
      "fields": [
        {
          "fieldPath": "templateId",
          "order": "ASCENDING"
        },
        {
          "fieldPath": "submittedAt",
          "order": "DESCENDING"
        },
        {
          "fieldPath": "__name__",
          "order": "DESCENDING"
        }
      ]
    }
  ],
  "fieldOverrides": []
}
